Metadata-Version: 2.1
Name: OTPpy
Version: 0.1.2
Summary: OTP library for Python 3
Home-page: https://github.com/bitlogik/OTPpy
Author: BitLogiK
Author-email: contact@bitlogik.fr
License: GPLv3
Keywords: otppy otp security hotp totp 2FA
Platform: UNKNOWN
Classifier: Programming Language :: Python :: 3 :: Only
Classifier: License :: OSI Approved :: GNU General Public License v3 (GPLv3)
Classifier: Intended Audience :: Developers
Classifier: Intended Audience :: Information Technology
Classifier: Topic :: Security :: Cryptography
Classifier: Topic :: Software Development :: Libraries :: Python Modules
Requires-Python: >=3.4
Provides-Extra: dev
License-File: LICENSE
